{"chapter": 16, "corrections": [{"v":8,"level":"l1","new":"Erkennend aber sprach Jesus: Was überlegt ihr bei euch selbst, ihr Kleingläubigen, dass ihr keine Brote genommen habt?","reason":"Der bisherige Text „Erkannt habend es aber“ ist ungrammatisch: das pronominale Objekt „es“ ist falsch zwischen Partizip und „aber“ eingeschoben und steht zudem nicht im Urtext (γνοὺς δὲ hat kein ausgedrücktes Objekt). Wiedergabe als vorangestelltes Partizip „Erkennend aber“ folgt der l1-Partizipkonvention (vgl. ἀποκριθεὶς εἶπεν → „antwortend sprach er“), bleibt konkordant und ohne Zusatz. Der Vorschlag des Erstprüfers behebt zwar die Wortstellung, fügt aber mit „Dies“ erneut ein im Griechischen nicht vorhandenes Objekt ein; daher minimal nachgebessert.","severity":"niedrig"}], "summary":"Eine berechtigte Korrektur: Der einzige vorgeschlagene Eingriff (V. 8 l1) behebt einen echten grammatischen Mangel in der Wortstellung. Da der Vorschlag selbst mit „Dies“ ein nicht im Urtext stehendes Objekt einführte, wurde er auf eine objektlose, konkordante Partizipform („Erkennend aber“) nachgebessert. Die übrigen Verse waren bereits korrekt und registergerecht."}
