{"chapter":130,"verses":[
{"v":1,"l1":"Ein Lied der Aufstiege. Aus den Tiefen rufe ich dich an, HERR.","l3":"Ein Wallfahrtslied. Aus den tiefsten Tiefen rufe ich zu dir, HERR."},
{"v":2,"l1":"Herr, hore auf meine Stimme; lass deine Ohren aufmerksam sein auf die Stimme meines Flehens.","l3":"Herr, hor mich an! Hab ein offenes Ohr fur mein flehendes Rufen."},
{"v":3,"l1":"Wenn du Verschuldungen bewahrst, HERR, Herr, wer kann bestehen?","l3":"Wenn du, HERR, jede Schuld festhieltest, Herr, wer konnte dann noch bestehen?"},
{"v":4,"l1":"Doch bei dir ist die Vergebung, damit man dich furchte.","l3":"Aber bei dir ist Vergebung, damit die Menschen Ehrfurcht vor dir haben."},
{"v":5,"l1":"Ich hoffe auf den HERRN, es hofft meine Seele, und auf sein Wort warte ich.","l3":"Ich warte auf den HERRN, mit ganzer Seele warte ich, und auf sein Wort hoffe ich."},
{"v":6,"l1":"Meine Seele wartet auf den Herrn mehr als Wachter auf den Morgen, Wachter auf den Morgen.","l3":"Ich sehne mich nach dem Herrn, mehr als Wachter den Morgen herbeisehnen, ja, mehr als Wachter den Morgen."},
{"v":7,"l1":"Warte, Israel, auf den HERRN! Denn bei dem HERRN ist die Gute, und reichlich ist bei ihm Erlosung.","l3":"Hoffe, Israel, auf den HERRN! Denn beim HERRN ist Gute, und reiche Erlosung gibt es bei ihm."},
{"v":8,"l1":"Und er, er wird Israel erlosen aus allen seinen Verschuldungen.","l3":"Er selbst wird Israel von all seiner Schuld befreien."}
],"stage":"final"}
