{"chapter":149,"verses":[
{"v":1,"l1":"Halleluja! Singt dem HERRN ein neues Lied, sein Lob in der Versammlung der Frommen.","l3":"Halleluja! Singt dem HERRN ein neues Lied, singt sein Lob in der Gemeinde derer, die ihm treu sind."},
{"v":2,"l1":"Es freue sich Israel an seinem Schöpfer, die Söhne Zions sollen jubeln über ihren König.","l3":"Israel soll sich freuen an dem, der es geschaffen hat, die Kinder Zions sollen jubeln über ihren König."},
{"v":3,"l1":"Sie sollen seinen Namen loben im Reigen, mit Pauke und Leier ihm spielen.","l3":"Sie sollen seinen Namen loben mit Tanz, ihm Musik machen auf Trommel und Harfe."},
{"v":4,"l1":"Denn der HERR hat Gefallen an seinem Volk, er schmückt die Demütigen mit Rettung.","l3":"Denn der HERR hat Freude an seinem Volk, er schenkt den Gebeugten Rettung als Schmuck."},
{"v":5,"l1":"Es sollen frohlocken die Frommen in Herrlichkeit, sie sollen jauchzen auf ihren Lagern.","l3":"Die ihm treu sind, sollen voll Freude jubeln, sie sollen vor Freude singen, selbst auf ihren Betten."},
{"v":6,"l1":"Hocherhebungen Gottes in ihrer Kehle, und ein zweischneidiges Schwert in ihrer Hand,","l3":"Das Loblied auf Gott im Mund und ein zweischneidiges Schwert in der Hand,"},
{"v":7,"l1":"um Rache zu üben an den Völkern, Züchtigungen an den Nationen,","l3":"um an den Völkern Vergeltung zu üben und die Nationen zu strafen,"},
{"v":8,"l1":"um zu binden ihre Könige mit Ketten und ihre Geehrten mit eisernen Fesseln,","l3":"um ihre Könige in Ketten zu legen und ihre Vornehmen in eiserne Fesseln,"},
{"v":9,"l1":"um an ihnen zu vollziehen das geschriebene Recht. Eine Ehre ist das für alle seine Frommen. Halleluja!","l3":"um an ihnen das Urteil zu vollstrecken, das aufgeschrieben ist. Das ist die Ehre aller, die ihm treu sind. Halleluja!"}
],"stage":"final"}
